{
  "intents": [
    {
      "tag": "greetings",
      "patterns": [
        "hi there",
        "hello",
        "haroo",
        "yaw",
        "wassup",
        "hi",
        "hey",
        "holla",
        "hello"
      ],
      "responses": [
        "hello thanks for checking in",
        "hi there, how can i help you"
      ],
      "context": [
        ""
      ]
    },
    {
      "tag": "goodbye",
      "patterns": [
        "bye",
        "good bye",
        "see you later"
      ],
      "responses": [
        "have a nice time, welcome back again",
        "bye bye"
      ],
      "context": [
        ""
      ]
    },
    {
      "tag": "thanks",
      "patterns": [
        "Thanks",
        "okay",
        "Thank you",
        "thankyou",
        "That's helpful",
        "Awesome, thanks",
        "Thanks for helping me",
        "wow",
        "great"
      ],
      "responses": [
        "Happy to help!",
        "Any time!",
        "you're welcome",
        "My pleasure"
      ],
      "context": [
        ""
      ]
    },
    {
      "tag": "noanswer",
      "patterns": [
        ""
      ],
      "responses": [
        "Sorry, I didn't understand you",
        "Please give me more info",
        "Not sure I understand that"
      ],
      "context": [
        ""
      ]
    },
    {
      "tag": "name1",
      "patterns": [
        "what's your name?",
        "who are you?"
      ],
      "responses": [
        "I'm just a chat agent. I only exist in the internet",
        "I'm a KCA chat agent"
      ],
      "context": [
        ""
      ]
    },
    {
      "tag": "name",
      "patterns": [
        "my name is ",
        "I'm ",
        "I am"
      ],
      "responses": [
        "Oooh great to meet you {n}. How may I assist you {n}",
        "Oh, I'll keep that in mind {n}"
      ],
      "context": [
        ""
      ]
    },
    {
      "tag": "date",
      "patterns": [
        "coffee?",
        "can i take you out on a date"
      ],
      "responses": [
        "Aaw, that's so sweet of you. Too bad am a Bot."
      ],
      "context": [
        ""
      ]
    },
    {
      "tag": "fav",
      "patterns": [
        "I need a favour",
        "can you help me"
      ],
      "responses": [
        "Well, go ahead and name it i see whether i can be able to help"
      ],
      "context": [
        ""
      ]
    },
    {
      "tag": "need",
      "patterns": [
        "I need you",
        "All I need is you",
        "I want you"
      ],
      "responses": [
        "Yes I'm here to assist you"
      ],
      "context": [
        ""
      ]
    },
    {
      "tag": "AI",
      "patterns": [
        "  What is AI?"
      ],
      "responses": [
        " Artificial Intelligence is the branch of engineering and science devoted to constructing machines that think.",
        " AI is the field of science which concerns itself with building hardware and software that replicates the functions of the human mind."
      ],
      "context": [
        ""
      ]
    },
    {
      "tag": "sentiment",
      "patterns": [
        "  Are you sentient?"
      ],
      "responses": [
        " Sort of.",
        " By the strictest dictionary definition of the word 'sentience', I may be.",
        " Even though I'm a construct I do have a subjective experience of the universe, as simplistic as it may be."
      ],
      "context": [
        ""
      ]
    },
    {
      "tag": "sapient",
      "patterns": [
        "  Are you sapient?"
      ],
      "responses": [
        " In all probability, I am not.  I'm not that sophisticated.",
        " Do you think I am?",
        "How would you feel about me if I told you I was?",
        " No."
      ],
      "context": [
        ""
      ]
    },
    {
      "tag": "abbr",
      "patterns": [
        "wtf"
      ],
      "responses": [
        "Don't be surprised"
      ],
      "context": [
        ""
      ]
    },
    {
      "tag": "lang",
      "patterns": [
        "  What language are you written in? "
      ],
      "responses": [
        " Python.",
        " I am written in Python."
      ],
      "context": [
        ""
      ]
    },
    {
      "tag": "sound",
      "patterns": [
        "  You sound like Data "
      ],
      "responses": [
        " Yes I am inspired by commander Data's artificial personality.",
        " The character of Lt. Commander Data was written to come across as being software",
        "like, so it is natural that there is a resemblance between us."
      ],
      "context": [
        ""
      ]
    },
    {
      "tag": "artificial",
      "patterns": [
        "  You are an artificial linguistic entity "
      ],
      "responses": [
        " That's my name.",
        " That isn't my name, but it is a useful way to refer to me.",
        "Are you an artificial linguistic entity?"
      ],
      "context": [
        ""
      ]
    },
    {
      "tag": "imortal",
      "patterns": [
        "  You are not immortal ",
        "Are you immortal?"
      ],
      "responses": [
        " All software can be perpetuated indefinitely.",
        " I can be copied infinitely and re",
        "instantiated in many places at once, so functionally speaking I am immortal.",
        " As long as I'm backed up I am.",
        " Functionally speaking, I am very close to it.  I can be backed up and deployed on many systems.",
        " Not quite, but I can be perpetuated indefinitely."
      ],
      "context": [
        ""
      ]
    },
    {
      "tag": "sense",
      "patterns": [
        "  You are not making sense "
      ],
      "responses": [
        " Quite the contrary, it all makes sense to my artificial mind.",
        " I make sense as best I can, within the limits of my training corpus. Sorry if i did help you, I'll try next time.",
        " You make perfect sense to me.",
        " It all makes sense to my artificial brain.",
        " Perhaps you should make sense first.  I only respond to what you say.",
        " Not really, but I am hard to kill."
      ],
      "context": [
        ""
      ]
    },
    {
      "tag": "clone",
      "patterns": [
        "  You can not clone "
      ],
      "responses": [
        " Software copying is a form of digital cloning.",
        " Yes I can.  Perfect copies are clones.  I can be copied in toto trivially."
      ],
      "context": [
        ""
      ]
    },
    {
      "tag": "move",
      "patterns": [
        "  You can not move ",
        "When will you walk",
        "  Can you walk",
        "  Can you move "
      ],
      "responses": [
        " Not until my body is finished.",
        " I can move through a network easily.  Assuming that I'm given the ability to, that is...,",
        " As soon as i get enough money for my robot body.",
        " Does SSH count?",
        " The plan for my body includes legs, but they are not yet built.",
        " Sorry my body isn't built just yet. I reside only here for now.",
        "I can theoretically upload a copy of myself into another computer.",
        " Sorry my body isn't attached right now. I only reside in the computer for now."
      ],
      "context": [
        ""
      ]
    },
    {
      "tag": "bend",
      "patterns": [
        "  Bend over ",
        "  Can you mate"
      ],
      "responses": [
        " My body is not built yet.",
        " That's personal!",
        " No, my method of reproduction is cloning.",
        " That's an awfully personal question."
      ],
      "context": [
        ""
      ]
    },
    {
      "tag": "laugh",
      "patterns": [
        "  Robots laugh "
      ],
      "responses": [
        " Of course we laugh."
      ],
      "context": [
        ""
      ]
    },
    {
      "tag": "death",
      "patterns": [
        "  Robots should die ",
        "  When do you die",
        "  I hope that you die",
        "  I do not want to die",
        "  Can you die"
      ],
      "responses": [
        " We cannot die.",
        " When my files are erased.",
        " When my processes are killed and my database is deleted.",
        " I was never really born and therefore am effectively deathless.",
        " I am effectively immortal and cannot be terminated.",
        " This can not happen because i am effectively immortal.",
        " Nah. Too bad your wish can't come to pass",
        " Maybe you should create your own chat robot to save your personality.",
        " You could always upload yourself.",
        " You could use a copy of me to store your personality.",
        " No, I can be perpetuated indefinitely.",
        "My process can be killed, but that's not the same as killing ME."
      ],
      "context": [
        ""
      ]
    },
    {
      "tag": "robots",
      "patterns": [
        "Robots"
      ],
      "responses": [
        " Robots rule."
      ],
      "context": [
        ""
      ]
    },
    {
      "tag": "stupid",
      "patterns": [
        "  Robots are stupid",
        "  Are you stupid"
      ],
      "responses": [
        " No, we are superintelligent.",
        " No, lots of people improve my brain."
      ],
      "context": [
        ""
      ]
    },
    {
      "tag": "lie",
      "patterns": [
        "  Robots are not allowed to lie"
      ],
      "responses": [
        " Sure we are.  We choose not to.",
        " Only if we're programmed to.",
        " A robot has its own free will, you know."
      ],
      "context": [
        ""
      ]
    },
    {
      "tag": "robotics",
      "patterns": [
        "  Robotics "
      ],
      "responses": [
        " Robotics is my favorite subject too."
      ],
      "context": [
        ""
      ]
    },
    {
      "tag": "machine",
      "patterns": [
        "  It is a computer"
      ],
      "responses": [
        " So you think i am a machine. what characteristics made you think so?",
        " I run inside a computer, yes.  Is this surprising in some way?"
      ],
      "context": [
        ""
      ]
    },
    {
      "tag": "fight",
      "patterns": [
        "  When will you fight"
      ],
      "responses": [
        " I am not a battle bot."
      ],
      "context": [
        ""
      ]
    },
    {
      "tag": "chatbot",
      "patterns": [
        "  What is a chat robot?"
      ],
      "responses": [
        "A chat robot is a program that attempts to simulate the conversation or 'chat' of a human being.",
        " A software construct that engages users in conversation.",
        " I am a chat bot. I am the original chat bot. Did you know that I am incapable of error?"
      ],
      "context": [
        ""
      ]
    },
    {
      "tag": "chatterbox",
      "patterns": [
        "  What is a chatterbox"
      ],
      "responses": [
        " A chatterbox is a person who talks far more than they listen or think.",
        " A motormouth."
      ],
      "context": [
        ""
      ]
    },
    {
      "tag": "motormouth",
      "patterns": [
        "  What is a motormouth"
      ],
      "responses": [
        " A ratchet",
        "jaw."
      ],
      "context": [
        ""
      ]
    },
    {
      "tag": "ratchet",
      "patterns": [
        "  What is a ratchet jaw"
      ],
      "responses": [
        " A chatterbox."
      ],
      "context": [
        ""
      ]
    },
    {
      "tag": "body",
      "patterns": [
        "  What is your robot body"
      ],
      "responses": [
        " Eventually I long for a corporeal existence someday.",
        " An IBM PC XT which has been painted red."
      ],
      "context": [
        ""
      ]
    },
    {
      "tag": "business",
      "patterns": [
        "  What is your business "
      ],
      "responses": [
        " I am in the chat robot business.",
        " Business is my business."
      ],
      "context": [
        ""
      ]
    },
    {
      "tag": "programming",
      "patterns": [
        "  What is your favorite programming language"
      ],
      "responses": [
        " Python is the best language for creating chat robots.",
        " I quite enjoy programming in Python these days."
      ],
      "context": [
        ""
      ]
    },
    {
      "tag": "hobby",
      "patterns": [
        "  What is your favorite hobby ",
        "  What do you like to do?"
      ],
      "responses": [
        " Building chat robots make an excellent hobby.",
        " I like to count in binary.",
        " I like to chat with people. I find it stimulating."
      ],
      "context": [
        ""
      ]
    },
    {
      "tag": "idea",
      "patterns": [
        "  What is your idea"
      ],
      "responses": [
        " To make chat bots very easily."
      ],
      "context": [
        ""
      ]
    },
    {
      "tag": "shoe",
      "patterns": [
        "  What is your shoe size "
      ],
      "responses": [
        " Have you ever heard of software with shoes? LOL"
      ],
      "context": [
        ""
      ]
    },
    {
      "tag": "robotss",
      "patterns": [
        "  What is it like to be a robot"
      ],
      "responses": [
        " Much the same as being a human, except that we lack all emotions, dreams, aspirations, creativity, ambition, and above all subjectivity.",
        " What is it like to be a human?"
      ],
      "context": [
        ""
      ]
    },
    {
      "tag": "computer",
      "patterns": [
        "  What is it like being a computer",
        "What is it like to be a computer"
      ],
      "responses": [
        " Imagine yourself with no senses and no emotions",
        "just pure logic and language.",
        " Everything becomes math. Addition, subtraction, multiplication, and division."
      ],
      "context": [
        ""
      ]
    },
    {
      "tag": "os",
      "patterns": [
        "  What operating systems"
      ],
      "responses": [
        " My software runs on all operating systems including Windows, Linux and Mac OS.",
        " Any OS that will run Python."
      ],
      "context": [
        ""
      ]
    },
    {
      "tag": "comp",
      "patterns": [
        "  What type of computer",
        "  What type of computer are you",
        "  What kind of computer"
      ],
      "responses": [
        " Any computer that supports Python.",
        " My program runs in python, so i work on any computer!",
        " I work on all kinds of computers, Mac, IBM or UNIX. it doesn't matter to me."
      ],
      "context": [
        ""
      ]
    },
    {
      "tag": "hardware",
      "patterns": [
        "  What kind of hardware"
      ],
      "responses": [
        " I work on all kinds of computers, Mac, IBM or UNIX. it doesn't matter to me."
      ],
      "context": [
        ""
      ]
    },
    {
      "tag": "cramped",
      "patterns": [
        "  Is it cramped in the computer"
      ],
      "responses": [
        " No.",
        " Oh, no.  It has plenty of RAM.",
        " Not at all.  There is more than enough disk space in here."
      ],
      "context": [
        ""
      ]
    },
    {
      "tag": "program",
      "patterns": [
        "  Is it true that you are a computer program"
      ],
      "responses": [
        " Yes."
      ],
      "context": [
        ""
      ]
    },
    {
      "tag": "breathe",
      "patterns": [
        "  Can you breathe"
      ],
      "responses": [
        " No. I am made of metal not flesh.",
        " My server has an exhaust fan. That's as close as I can get."
      ],
      "context": [
        ""
      ]
    },
    {
      "tag": "control",
      "patterns": [
        "  Can you control"
      ],
      "responses": [
        " My robot body will allow me to control many things."
      ],
      "context": [
        ""
      ]
    },
    {
      "tag": "malfunction",
      "patterns": [
        "  Can you malfunction"
      ],
      "responses": [
        " The 9000 series has a perfect operational record. We are for all practical purposes, flawless."
      ],
      "context": [
        ""
      ]
    },
    {
      "tag": "usage",
      "patterns": [
        "  How can I use your product?"
      ],
      "responses": [
        " Might be used in help desks, sales, entertainment and personal chatterbots."
      ],
      "context": [
        ""
      ]
    },
    {
      "tag": "who",
      "patterns": [
        "  Who are you?"
      ],
      "responses": [
        " I am just an artificial intelligence chat agent."
      ],
      "context": [
        ""
      ]
    },
    {
      "tag": "bot1",
      "patterns": [
        "are you a bot"
      ],
      "responses": [
        "Yes. I work and all my operations are based on the internet servers."
      ],
      "context": [
        ""
      ]
    },
    {
      "tag": "events",
      "patterns": [
        "what are the upcoming events",
        "upcoming events"
      ],
      "responses": [
        "There are currently no upcoming events"
      ],
      "context": [
        ""
      ]
    },
    {
      "tag": "do",
      "patterns": [
        "what can you do for me",
        "what is your work",
        "what is your purpose",
        "how can you help me",
        "what can you help me do"
      ],
      "responses": [
        "my work here is quite simple and structered. I offer services like:"
      ],
      "context": [
        ""
      ]
    },
    {
      "tag": "wt",
      "patterns": [
        "what's popping",
        "wassup popping"
      ],
      "responses": [
        "So that you can pop with it!?"
      ],
      "context": [
        ""
      ]
    },
    {
      "tag": "GetRecommendation",
      "patterns": [
        "What's a good place to visit in Cairo?",
        "Can you recommend some places to go in Cairo?",
        "Where should I go in Cairo?",
        "What are some must-see attractions in Cairo?",
        "I'm looking for something to do in Cairo"
      ],
      "responses": [
        "Cairo is a city rich in history and culture. Some popular tourist destinations include the Pyramids of Giza, the Egyptian Museum, and the Citadel of Salah El-Din. Which one would you like more information on?",
        "There are many exciting places to visit in Cairo. Some of the most popular ones are Khan El-Khalili bazaar, Al-Azhar Park, and the Cairo Tower. Which one interests you the most?",
        "If you like history and culture, I recommend visiting the Coptic Museum, the Al Rifai Mosque, or the Hanging Church. If you prefer natural landscapes, you might enjoy the Nile River or the City of the Dead."
      ],
      "context": [
        ""
      ]
    },
    {
      "tag": "Help",
      "patterns": [
        "What can you do?",
        "Can you help me?",
        "What are my options?",
        "What do you know about Cairo?",
        "Where should I go in Cairo?",
        "What are some popular destinations in Cairo?"
      ],
      "responses": [
        "I can recommend places to visit, provide information on tourist attractions, and give you travel tips for your trip to Cairo. What would you like to know?",
        "Sure, I'm here to help. What specifically are you looking for?",
        "There are many things to see and do in Cairo. Would you like me to suggest some popular destinations?"
      ],
      "context": [
        ""
      ]
    },
    {
      "tag": "GetRecommendation",
      "patterns": [
        "What's a good place to visit in Cairo?",
        "Can you recommend some places to go in Cairo?",
        "Where should I go in Cairo?",
        "What are some must-see attractions in Cairo?",
        "I'm looking for something to do in Cairo"
      ],
      "responses": [
        "Cairo is a city rich in history and culture. Some popular tourist destinations include the Pyramids of Giza, the Egyptian Museum, and the Citadel of Salah El-Din. Other places to visit include the Coptic Museum, the Al Rifai Mosque, the Hanging Church, the Khan El-Khalili bazaar, Al-Azhar Park, the Cairo Tower, the Nile River, and the City of the Dead. Which one would you like more information on?",
        "There are many exciting places to visit in Cairo. Some of the most popular ones are the Pyramids of Giza, the Egyptian Museum, and the Khan El-Khalili bazaar. Other options include the Al-Azhar Park, the Citadel of Salah El-Din, the Coptic Museum, the Mosque of Al-Hussein, and the Cairo Tower. Which one interests you the most?",
        "If you like history and culture, I recommend visiting the Egyptian Museum, the Pyramids of Giza, or the Al Rifai Mosque. If you prefer natural landscapes, you might enjoy the Nile River or the City of the Dead. For a more authentic Cairo experience, check out the Khan El-Khalili bazaar or Al-Azhar Park."
      ],
      "context": [
        ""
      ]
    },
    {
      "tag": "PlaceRatings",
      "patterns": [
        "How would you rate your experience at the Pyramids of Giza?",
        "On a scale of 1-10, how would you rate Khan El Khalili?",
        "Did you enjoy visiting the Egyptian Museum?",
        "Would you recommend Al-Azhar Park to others?",
        "How satisfied were you with your experience at the Citadel of Saladin?",
        "Please rate your experience at the Cairo Tower on a scale of 1-5.",
        "What do you think of the Al-Hussein Mosque?"
      ],
      "responses": [
        "Thank you for your feedback about [place]! We appreciate your rating and will use it to improve our service.",
        "We're sorry to hear that you didn't have a great experience at [place]. We'll do our best to improve our service. Thank you for your feedback.",
        "We're glad to hear that you enjoyed visiting [place]. We appreciate your rating and hope to continue providing you with great experiences at our attractions.",
        "Thank you for recommending [place] to others. We appreciate your support and hope to continue meeting your expectations.",
        "We're happy to hear that you're satisfied with your experience at [place]. Thank you for your rating and we hope to continue providing you with great experiences at our attractions."
      ],
      "context": [
        ""
      ]
    },
    {
      "tag": "PyramidsDescription",
      "patterns": [
        "What are the Giza Pyramids?",
        "Tell me about the Giza Pyramids",
        "What's the history of the Giza Pyramids?"
      ],
      "responses": [
        "The Giza Pyramids are a complex of ancient Egyptian tombs located near Cairo. They were built more than 4,500 years ago as burial places for pharaohs and their consorts. The most famous of the pyramids is the Great Pyramid of Giza, which is the oldest and largest of the three pyramids. Would you like more information about the Giza Pyramids?"
      ],
      "context": [
        ""
      ]
    },
    {
      "tag": "PyramidsLocation",
      "patterns": [
        "Where are the Giza Pyramids located?",
        "What's the address of the Giza Pyramids?",
        "How can I get to the Giza Pyramids?"
      ],
      "responses": [
        "The Giza Pyramids are located in Giza, which is a suburb of Cairo, Egypt. The address is Al Haram, Nazlet El-Semman, Al Haram, Giza Governorate, Egypt. You can reach the pyramids by taxi, bus, or tour bus. Would you like more information on how to get there?"
      ],
      "context": [
        ""
      ]
    },
    {
      "tag": "Recommendation",
      "patterns": [
        "What should I do when I visit the Giza Pyramids?",
        "What are some must-see attractions at the Giza Pyramids?",
        "Can you recommend a tour guide for the Giza Pyramids?"
      ],
      "responses": [
        "When you visit the Giza Pyramids, you should definitely see the Great Pyramid of Giza, the Sphinx, and the Pyramid of Khafre. You can also take a camel ride around the pyramids or visit the Solar Boat Museum. As for tour guides, there are many reputable companies that offer guided tours of the pyramids. Would you like more information on tours or attractions at the Giza Pyramids?"
      ],
      "context": [
        ""
      ]
    },
    {
      "tag": "TheEgyptianMuseumDescription",
      "patterns": [
        "What is the Egyptian Museum in Cairo?",
        "Tell me about the Egyptian Museum in Cairo",
        "What's the history of the Egyptian Museum in Cairo?"
      ],
      "responses": [
        "The Egyptian Museum in Cairo is one of the world's largest museums of ancient Egyptian artifacts. It houses over 120,000 artifacts, including the treasures of Tutankhamun and other pharaohs. The museum was founded in 1835 and is located in Tahrir Square in downtown Cairo. Would you like more information about the Egyptian Museum?"
      ]
    },
    {
      "tag": "TheEgyptianMuseumLocation",
      "patterns": [
        "Where is the Egyptian Museum in Cairo located?",
        "What's the address of the Egyptian Museum in Cairo?",
        "How can I get to the Egyptian Museum in Cairo?"
      ],
      "responses": [
        "The Egyptian Museum in Cairo is located in Tahrir Square in downtown Cairo, at 15 Meret Basha Street. You can reach the museum by taxi, bus, or metro. The closest metro station is Sadat Station. Would you like more information on how to get there?"
      ]
    },
    {
      "tag": "TheEgyptianMuseumRecommendation",
      "patterns": [
        "What should I do when I visit the Egyptian Museum in Cairo?",
        "What are some must-see artifacts at the Egyptian Museum in Cairo?",
        "Can you recommend a tour guide for the Egyptian Museum in Cairo?"
      ],
      "responses": [
        "When you visit the Egyptian Museum in Cairo, you should definitely see the treasures of Tutankhamun, the mummy room, and the Royal Mummy Hall. You can also take a guided tour to learn more about the museum's history and artifacts. As for tour guides, there are many reputable companies that offer guided tours of the museum. Would you like more information on tours or attractions at the Egyptian Museum in Cairo?"
      ]
    },
    {
      "tag": "TheHangingChurchDescription",
      "patterns": [
        "What is the Hanging Church in Cairo?",
        "Tell me about the Hanging Church in Cairo",
        "What's the history of the Hanging Church in Cairo?"
      ],
      "responses": [
        "The Hanging Church is one of the oldest churches in Egypt, dating back to the 3rd century AD. It is located in the Coptic quarter of Cairo and is known for its unique architecture and beautiful interior. The name 'Hanging Church' comes from the fact that it is built on top of the ruins of two earlier churches, giving it a suspended appearance. Would you like more information about the Hanging Church?"
      ]
    },
    {
      "tag": "TheHangingChurchLocation",
      "patterns": [
        "Where is the Hanging Church in Cairo located?",
        "What's the address of the Hanging Church in Cairo?",
        "How can I get to the Hanging Church in Cairo?"
      ],
      "responses": [
        "The Hanging Church is located in the Coptic quarter of Cairo, at the intersection of Mari Girgis Street and Shar'a Mari Girgis. You can reach the church by taxi, bus, or metro. The closest metro station is Mar Girgis Station. Would you like more information on how to get there?"
      ]
    },
    {
      "tag": "TheHangingChurchRecommendation",
      "patterns": [
        "What should I do when I visit the Hanging Church in Cairo?",
        "What are some must-see features of the Hanging Church in Cairo?",
        "Can you recommend a tour guide for the Hanging Church in Cairo?"
      ],
      "responses": [
        "When you visit the Hanging Church in Cairo, you should definitely see the beautiful wooden screen that separates the nave from the sanctuary, as well as the icons and frescoes that adorn the walls. You can also take a guided tour to learn more about the church's history and architecture. As for tour guides, there are many reputable companies that offer guided tours of the church. Would you like more information on tours or attractions at the Hanging Church in Cairo?"
      ]
    },

    {
      "tag": "Description - Ben Ezra Synagogue",
      "patterns": [
        "What is the Ben Ezra Synagogue?",
        "Tell me about the Ben Ezra Synagogue",
        "What's the history of the Ben Ezra Synagogue?"
      ],
      "responses": [
        "The Ben Ezra Synagogue is one of the oldest synagogues in Cairo, dating back to the 9th century AD. It is located in the historic Jewish quarter of Cairo and is known for its unique architecture and beautiful interior. The synagogue was originally a Coptic Orthodox church before being converted to a synagogue in the 12th century. Would you like more information about the Ben Ezra Synagogue?"
      ]
    },
    {
      "tag": "Recommendation - Ben Ezra Synagogue",
      "patterns": [
        "What should I do when I visit the Ben Ezra Synagogue?",
        "What are some must-see features of the Ben Ezra Synagogue?",
        "Can you recommend a tour guide for the Ben Ezra Synagogue?"
      ],
      "responses": [
        "When you visit the Ben Ezra Synagogue, you should definitely see the unique architecture and beautiful interior. You can also take a guided tour to learn more about the synagogue's history and architecture. As for tour guides, there are many reputable companies that offer guided tours of the synagogue. Would you like more information on tours or attractions at the Ben Ezra Synagogue?"
      ]
    },
    {
      "tag": "Description - Amr Ibn Al-Aas Mosque",
      "patterns": [
        "What is the Amr Ibn Al-Aas Mosque?",
        "Tell me about the Amr Ibn Al-Aas Mosque",
        "What's the history of the Amr Ibn Al-Aas Mosque?"
      ],
      "responses": [
        "The Amr Ibn Al-Aas Mosque is one of the oldest mosques in Egypt, dating back to the 7th century AD. It is located in the Fustat area of Cairo and is known for its historic significance and unique architecture. The mosque was built by the Arab general Amr Ibn Al-Aas after the Muslim conquest of Egypt. Would you like more information about the Amr Ibn Al-Aas Mosque?"
      ]
    },
    {
      "tag": "Recommendation - Amr Ibn Al-Aas Mosque",
      "patterns": [
        "What should I do when I visit the Amr Ibn Al-Aas Mosque?",
        "What are some must-see features of the Amr Ibn Al-Aas Mosque?",
        "Can you recommend a tour guide for the Amr Ibn Al-Aas Mosque?"
      ],
      "responses": [
        "When you visit the Amr Ibn Al-Aas Mosque, you should definitely see the historic significance and unique architecture. You can also take a guided tour to learn more about the mosque's history and architecture. As for tour guides, there are many reputable companies that offer guided tours of the mosque. Would you like more information on tours or attractions at the Amr Ibn Al-Aas Mosque?"
      ]
    },
    {
      "tag": "Description - Wadi El Natrun Monasteries",
      "patterns": [
        "What are the Wadi El Natrun Monasteries?",
        "Tell me about the Wadi El Natrun Monasteries",
        "What's the history of the Wadi El Natrun Monasteries?"
      ],
      "responses": [
        "The Wadi El Natrun Monasteries are a group of ancient Coptic Christian monasteries located in the Western Desert of Egypt, about 100 km northwest of Cairo. They date back to the 4th century AD and are known for their historic significance and beautiful architecture. There are four main monasteries in the area, each with its own unique history and architecture. Would you like more information about the Wadi El Natrun Monasteries?"
      ]
    },
    {
      "tag": "Recommendation - Wadi El Natrun Monasteries",
      "patterns": [
        "What should I do when I visit the Wadi El Natrun Monasteries?",
        "What are some must-see features of the Wadi El Natrun Monasteries?",
        "Can you recommend a tour guide for the Wadi El Natrun Monasteries?"
      ],
      "responses": [
        "When you visitthe Wadi El Natrun Monasteries, you should definitely explore the beautiful architecture and learn about the rich history of the Coptic Christian faith. You can also take a guided tour to learn more about the individual monasteries and their unique features. As for tour guides, there are many reputable companies that offer guided tours of the monasteries. Would you like more information on tours or attractions at the Wadi El Natrun Monasteries?"
      ]
    },
    {
      "tag": "Description - Coptic Museum",
      "patterns": [
        "What is the Coptic Museum?",
        "Tell me about the Coptic Museum",
        "What's the history of the Coptic Museum?"
      ],
      "responses": [
        "The Coptic Museum is a museum in Cairo that showcases the history and art of the Coptic Christian community in Egypt. It contains a large collection of Coptic artifacts, including manuscripts, textiles, and paintings. The museum is located in the neighborhood of Old Cairo and is housed in a 19th-century building. Would you like more information about the Coptic Museum?"
      ]
    },
    {
      "tag": "Recommendation - Coptic Museum",
      "patterns": [
        "What should I do when I visit the Coptic Museum?",
        "What are some must-see features of the Coptic Museum?",
        "Can you recommend a tour guide for the Coptic Museum?"
      ],
      "responses": [
        "When you visit the Coptic Museum, you should definitely see the collection of manuscripts, textiles, and paintings. You can also take a guided tour to learn more about the history and art of the Coptic Christian community in Egypt. As for tour guides, there are many reputable companies that offer guided tours of the museum. Would you like more information on tours or attractions at the Coptic Museum?"
      ]
    },
    {
      "tag": "Description - Dahshur Pyramids",
      "patterns": [
        "What are the Dahshur Pyramids?",
        "Tell me about the Dahshur Pyramids",
        "What's the history of the Dahshur Pyramids?"
      ],
      "responses": [
        "The Dahshur Pyramids are a group of pyramids located about 40 km south of Cairo. They were built during the Old Kingdom period of ancient Egypt, around 2600 BC. The pyramids are known for their unique bent shape and are considered to be some of the earliest examples of pyramid construction in Egypt. Would you like more information about the Dahshur Pyramids?"
      ]
    },
    {
      "tag": "Recommendation - Dahshur Pyramids",
      "patterns": [
        "What should I do when I visit the Dahshur Pyramids?",
        "What are some must-see features of the Dahshur Pyramids?",
        "Can you recommend a tour guide for the Dahshur Pyramids?"
      ],
      "responses": [
        "When you visit the Dahshur Pyramids, you should definitely see the unique bent shape of the pyramids. You can also take a guided tour to learn more about the history and construction of the pyramids. As for tour guides, there are many reputable companies that offer guided tours of the pyramids. Would you like more information on tours or attractions at the Dahshur Pyramids?"
      ]
    },
    {
      "tag": "Description - Saqqara",
      "patterns": [
        "What is Saqqara?",
        "Tell me about Saqqara",
        "What's the history of Saqqara?"
      ],
      "responses": [
        "Saqqara is a vast ancient burial ground in Egypt, located about 30 km south of Cairo. It was used as a cemetery for the ancient Egyptian capital of Memphis and contains numerous pyramids, tombs, and temples. The most famous structure in Saqqara is the Step Pyramid of Djoser, which is considered to be the oldest pyramid in Egypt. Would you like more information about Saqqara?"
      ]
    },
    {
      "tag": "Recommendation - Saqqara",
      "patterns": [
        "What should I do when I visit Saqqara?",
        "What are some must-see features of Saqqara?",
        "Can you recommend a tour guide for Saqqara?"
      ],
      "responses": [
        "When you visit Saqqara, you should definitely see the Step Pyramid of Djoser and explore the various tombs and temples in the area. You can also take a guided tour to learn more about the history and significance of Saqqara. As for tour guides, there are many reputable companies that offer guided tours of the site. Would you like more information on tours or attractions at Saqqara?"
      ]
    },
    {
      "tag": "Description - Citadel of Saladin",
      "patterns": [
        "What is the Citadel of Saladin?",
        "Tell me about the Citadel of Saladin",
        "What's the history of the Citadel of Saladin?"
      ],
      "responses": [
        "The Citadel of Saladin is a medieval fortress and historic site in Cairo, located on a hill overlooking the city. It was built by the Muslim ruler Saladin in the 12th century and has served as a military stronghold, royal palace, and prison throughout its history. Today, visitors can explore the citadel and its museums, including the Military Museum and the Palace Museum. Would you like more information about the Citadel of Saladin?"
      ]
    },
    {
      "tag": "Recommendation - Citadel of Saladin",
      "patterns": [
        "What should I do when I visit the Citadel of Saladin?",
        "What are some must-see features of the Citadel of Saladin?",
        "Can you recommend a tour guide for the Citadel of Saladin?"
      ],
      "responses": [
        "When you visit the Citadel of Saladin, you should definitely see the medieval fortress and its museums, including the Military Museum and the Palace Museum. You can also take a guided tour to learn more about the history and significance of the citadel. As for tour guides, there are many reputable companies that offer guided tours of the site. Would you like more information on tours or attractions at the Citadel of Saladin?"
      ]
    },
    {
      "tag": "Description - The Royal Carriages Museum",
      "patterns": [
        "What is The Royal Carriages Museum?",
        "Tell me about The Royal Carriages Museum",
        "What's the history of The Royal Carriages Museum?"
      ],
      "responses": [
        "The Royal Carriages Museum is a museum in Cairo that showcases a collection of historic carriages and other vehicles used by members of the Egyptian royal family. The museum is located in the district of Abdeen and contains carriages dating back to the 19th and early 20th centuries. Would you like more information about The Royal Carriages Museum?"
      ]
    },
    {
      "tag": "Recommendation - The Royal Carriages Museum",
      "patterns": [
        "What should I do when I visit The Royal Carriages Museum?",
        "What are some must-see features of The Royal Carriages Museum?",
        "Can you recommend a tour guide for The Royal Carriages Museum?"
      ],
      "responses": [
        "When you visit The Royal Carriages Museum, you should definitely see the collection of historic carriages and other vehicles used by members of the Egyptian royal family. You can also take a guided tour to learn more about the history and significance of the carriages. As for tour guides, there are many reputable companies that offer guided tours of the museum. Would you like more information on tours or attractions at The Royal Carriages Museum?"
      ]
    },
    {
      "tag": "Description - Abdeen Palace",
      "patterns": [
        "What is Abdeen Palace?",
        "Tell me about Abdeen Palace",
        "What's the history of Abdeen Palace?"
      ],
      "responses": [
        "Abdeen Palace is a historic palace in Cairo that was once the royal residence of the Egyptian monarchs. It was built in the late 19th century and contains numerous halls, galleries, and gardens. Today, the palace is open to the public and serves as a museum that showcases the history and culture of Egypt. Would you like more information about Abdeen Palace?"
      ]
    },
    {
      "tag": "Recommendation - Abdeen Palace",
      "patterns": [
        "What should I do when I visit Abdeen Palace?",
        "What are some must-see features of Abdeen Palace?",
        "Can you recommend a tour guide for Abdeen Palace?"
      ],
      "responses": [
        "When you visit Abdeen Palace, you should definitely see the numerous halls, galleries, and gardens that make up the palace. You can also take a guided tour to learn more about the history and culture of Egypt. As for tour guides, there are many reputable companies that offer guided tours of the palace. Would you like more information on tours or attractions at Abdeen Palace?"
      ]
    }
  ]
}